SiQt/__init__.py
SiQt/__main__.py
SiQt/_version.py
SiQt/definitions.py
SiQt/dep_resolv.py
SiQt/deployement.py
SiQt/logic_parser.py
SiQt/matplotlib.py
SiQt/siqt/__init__.py
SiQt/siqt/definitions.py
SiQt/siqt/dep_resolv.py
SiQt/siqt/deployement.py
SiQt/siqt/importers.py
SiQt/siqt/logic_parser.py
SiQt/siqt/matplotlib.py
SiQt/siqt/qtbase.py
SiQt/siqt/tests/__init__.py
SiQt/siqt/tests/run_suite.py
SiQt/siqt/tests/test_importers.py
SiQt/siqt/tests/test_logic.py
SiQt/siqt/widgets/__init__.py
SiQt/siqt/widgets/debug_information.py
SiQt/siqt/widgets/progress_bar.py
SiQt/tests/__init__.py
SiQt/tests/test_logic.py
SiQt/widgets/__init__.py
SiQt/widgets/debug_information.py
SiQt/widgets/progress_bar.py
SiQt-0.3.0.dist-info/DESCRIPTION.rst
SiQt-0.3.0.dist-info/METADATA
SiQt-0.3.0.dist-info/RECORD
SiQt-0.3.0.dist-info/WHEEL
SiQt-0.3.0.dist-info/metadata.json
SiQt-0.3.0.dist-info/top_level.txt
