Metadata-Version: 2.0
Name: SiQt
Version: 0.3.0
Summary: Convenience tools for building PyQt/PySide based GUI applications.
Home-page: https://github.com/symerio/SiQt
Author: Roman Yurchak
Author-email: rth.yurchak@gmail.com
License: MIT
Platform: UNKNOWN
Classifier: Development Status :: 4 - Beta
Classifier: Intended Audience :: Developers
Classifier: Topic :: Software Development :: Libraries :: Python Modules
Classifier: License :: OSI Approved :: MIT License
Classifier: Programming Language :: Python :: 3
Classifier: Programming Language :: Python :: 3.5
Classifier: Programming Language :: Python :: 3.6
Classifier: Programming Language :: Python :: 3.7
Requires-Dist: qtpy
